AlumniumBrowserPlugin/__init__.py
AlumniumBrowserPlugin/alumniumbrowserplugin.py
robotframework_alumniumbrowserplugin-0.1.4.dist-info/METADATA
robotframework_alumniumbrowserplugin-0.1.4.dist-info/WHEEL
robotframework_alumniumbrowserplugin-0.1.4.dist-info/entry_points.txt
robotframework_alumniumbrowserplugin-0.1.4.dist-info/RECORD
