Metadata-Version: 2.3
Name: robotframework-alumniumbrowserplugin
Version: 0.1.4
Summary: Alumnium AI plugin for the Robot Framework Browser Library
License: MIT
Author: Simon Meggle
Author-email: simon.meggle@elabit.de
Requires-Python: >=3.10,<4.0
Classifier: License :: OSI Approved :: MIT License
Classifier: Programming Language :: Python :: 3
Classifier: Programming Language :: Python :: 3.10
Classifier: Programming Language :: Python :: 3.11
Classifier: Programming Language :: Python :: 3.12
Classifier: Programming Language :: Python :: 3.13
Requires-Dist: alumnium (>=0.10.0)
Requires-Dist: robotframework (>=7,<8)
Requires-Dist: robotframework-browser (>=19,<20)
